outkast/__init__.py
outkast/secc_caste_ln.py
outkast/utils.py
outkast/data/secc/secc_all_state_year_ln_outkast.csv.gz
outkast-1.0.0.dist-info/licenses/LICENSE
outkast-1.0.0.dist-info/METADATA
outkast-1.0.0.dist-info/WHEEL
outkast-1.0.0.dist-info/entry_points.txt
outkast-1.0.0.dist-info/top_level.txt
outkast-1.0.0.dist-info/RECORD
