Metadata-Version: 2.4
Name: outkast
Version: 1.0.0
Summary: Infer Caste from Indian Names
Author-email: Gaurav Sood <gsood07@gmail.com>, Suriyan Laohaprapanon <suriyant@gmail.com>
License-Expression: MIT
Project-URL: Homepage, https://github.com/appeler/outkast
Project-URL: Repository, https://github.com/appeler/outkast
Project-URL: Issues, https://github.com/appeler/outkast/issues
Keywords: caste,names,india
Classifier: Development Status :: 3 - Alpha
Classifier: Intended Audience :: Developers
Classifier: Programming Language :: Python :: 3
Classifier: Programming Language :: Python :: 3.11
Classifier: Programming Language :: Python :: 3.12
Classifier: Programming Language :: Python :: 3.13
Classifier: Topic :: Scientific/Engineering :: Information Analysis
Classifier: Topic :: Software Development :: Libraries :: Python Modules
Classifier: Topic :: Utilities
Requires-Python: >=3.11
License-File: LICENSE
Requires-Dist: pandas>=0.19.2
Requires-Dist: numpy>=1.22.2
Provides-Extra: dev
Requires-Dist: check-manifest; extra == "dev"
Provides-Extra: test
Requires-Dist: coverage; extra == "test"
Requires-Dist: pytest; extra == "test"
Requires-Dist: pytest-cov; extra == "test"
Dynamic: license-file
